README.md
setup.cfg
setup.py
py_hcl/__init__.py
py_hcl/utils.py
py_hcl.egg-info/PKG-INFO
py_hcl.egg-info/SOURCES.txt
py_hcl.egg-info/dependency_links.txt
py_hcl.egg-info/requires.txt
py_hcl.egg-info/top_level.txt
py_hcl/compile/__init__.py
py_hcl/core/__init__.py
py_hcl/core/error/__init__.py
py_hcl/core/expr/__init__.py
py_hcl/core/expr/add.py
py_hcl/core/expr/and_.py
py_hcl/core/expr/bundle_holder.py
py_hcl/core/expr/convert.py
py_hcl/core/expr/extend.py
py_hcl/core/expr/field.py
py_hcl/core/expr/index.py
py_hcl/core/expr/io.py
py_hcl/core/expr/lit_sint.py
py_hcl/core/expr/lit_uint.py
py_hcl/core/expr/mod_inst.py
py_hcl/core/expr/or_.py
py_hcl/core/expr/slice.py
py_hcl/core/expr/vec_holder.py
py_hcl/core/expr/wire.py
py_hcl/core/expr/xor.py
py_hcl/core/expr/error/__init__.py
py_hcl/core/expr/utils/__init__.py
py_hcl/core/hcl_ops/__init__.py
py_hcl/core/module/__init__.py
py_hcl/core/module/base_module.py
py_hcl/core/module/meta_module.py
py_hcl/core/module/packed_module.py
py_hcl/core/module_factory/__init__.py
py_hcl/core/module_factory/extractor.py
py_hcl/core/module_factory/merger.py
py_hcl/core/module_factory/packer.py
py_hcl/core/module_factory/error/__init__.py
py_hcl/core/module_factory/inherit_list/__init__.py
py_hcl/core/module_factory/inherit_list/named_expr.py
py_hcl/core/module_factory/inherit_list/stmt_holder.py
py_hcl/core/stmt/__init__.py
py_hcl/core/stmt/branch.py
py_hcl/core/stmt/connect.py
py_hcl/core/stmt/error/__init__.py
py_hcl/core/stmt_factory/__init__.py
py_hcl/core/stmt_factory/scope.py
py_hcl/core/stmt_factory/trapper.py
py_hcl/core/type/__init__.py
py_hcl/core/type/bundle.py
py_hcl/core/type/clock.py
py_hcl/core/type/sint.py
py_hcl/core/type/uint.py
py_hcl/core/type/vector.py
py_hcl/core/type/wrapper.py
py_hcl/core/utils/__init__.py
py_hcl/dsl/__init__.py
py_hcl/dsl/branch.py
py_hcl/dsl/module.py
py_hcl/dsl/error/__init__.py
py_hcl/dsl/expr/__init__.py
py_hcl/dsl/expr/io.py
py_hcl/dsl/expr/wire.py
py_hcl/dsl/tpe/__init__.py
py_hcl/dsl/tpe/bundle.py
py_hcl/dsl/tpe/clock.py
py_hcl/dsl/tpe/sint.py
py_hcl/dsl/tpe/uint.py
py_hcl/error/__init__.py
py_hcl/firrtl_ir/__init__.py
