Metadata-Version: 2.1
Name: py-hcl
Version: 0.1.2
Summary: A Hardware Construct Language
Home-page: https://github.com/scutdig/pyhcl
Author: scutdig
Author-email: zhongzc_arch@outlook.com
License: MIT
Platform: UNKNOWN
Requires-Python: >=3.6
